icapservice/__init__.py
icapservice/content.py
icapservice/encapsulated.py
icapservice/handler.py
icapservice/messages.py
icapservice/request.py
icapservice/response.py
icapservice/service.py
icapservice-0.2.1.dist-info/DESCRIPTION.rst
icapservice-0.2.1.dist-info/METADATA
icapservice-0.2.1.dist-info/RECORD
icapservice-0.2.1.dist-info/WHEEL
icapservice-0.2.1.dist-info/metadata.json
icapservice-0.2.1.dist-info/top_level.txt
