Metadata-Version: 2.0
Name: icapservice
Version: 0.2.1
Summary: ICAP service library for Python
Home-page: https://github.com/gilesbrown/icapservice
Author: Giles Brown
Author-email: giles_brown@hotmail.com
License: MIT
Platform: UNKNOWN
Classifier: Development Status :: 3 - Alpha
Classifier: Intended Audience :: Developers
Classifier: Natural Language :: English
Classifier: License :: OSI Approved :: MIT License
Classifier: Programming Language :: Python
Classifier: Programming Language :: Python :: 2.7
Requires-Dist: brotlipy
Requires-Dist: six
